randd/__init__.py
randd/analyzer.py
randd/internal/__init__.py
randd/internal/estimator.py
randd/model/__init__.py
randd/model/base.py
randd/model/cubic.py
randd/model/linear.py
randd/model/pchip.py
randd/model/egrd/__init__.py
randd/model/egrd/egrd.py
randd/model/egrd/basis/psnr_100_6000_1080p.npz
randd/model/egrd/basis/psnr_100_6000_allres.npz
randd/model/egrd/basis/psnr_100_9000_1080p.npz
randd/model/egrd/basis/psnr_100_9000_allres.npz
randd/model/egrd/basis/ssimplus_100_6000_1080p.npz
randd/model/egrd/basis/ssimplus_100_6000_allres.npz
randd/model/egrd/basis/ssimplus_100_9000_1080p.npz
randd/model/egrd/basis/ssimplus_100_9000_allres.npz
randd/model/egrd/basis/vmaf_100_6000_1080p.npz
randd/model/egrd/basis/vmaf_100_6000_allres.npz
randd/model/egrd/basis/vmaf_100_9000_1080p.npz
randd/model/egrd/basis/vmaf_100_9000_allres.npz
randd-0.2.2.dist-info/LICENSE
randd-0.2.2.dist-info/METADATA
randd-0.2.2.dist-info/WHEEL
randd-0.2.2.dist-info/top_level.txt
randd-0.2.2.dist-info/RECORD
