Metadata-Version: 2.1
Name: randd
Version: 0.2.2
Summary: A Python Library for Video Codec Comparison.
Home-page: https://github.com/UWIVC/randd
Author: Wentao Liu, Zhengfang Duanmu
Author-email: liu.wen.tao90@gmail.com, alexduanmu@gmail.com
License: MIT License
Project-URL: Bug Reports, https://github.com/UWIVC/randd/issues
Project-URL: Source, https://github.com/UWIVC/randd/
Keywords: rate-distortion performance,video encoding
Classifier: Development Status :: 3 - Alpha
Classifier: Intended Audience :: Developers
Classifier: Topic :: Multimedia :: Video
Classifier: Programming Language :: Python :: 3
Classifier: Programming Language :: Python :: 3.10
Classifier: Programming Language :: Python :: 3 :: Only
Requires-Python: >=3.10, <4
License-File: LICENSE
Requires-Dist: numpy
Requires-Dist: scipy
Requires-Dist: osqp <1.0.0
Provides-Extra: dev
Requires-Dist: flake8 ; extra == 'dev'
Requires-Dist: pytest ; extra == 'dev'
